Metadata-Version: 2.1
Name: file2
Version: 0.1.10
Summary: File opener for gzip, bzip2, xz, or uncompressed files.
Home-page: https://github.com/alexmarder/file2
Author: Alex Marder
Requires-Python: >3.6
